esprovision.py
esprovision-0.1.dist-info/METADATA
esprovision-0.1.dist-info/WHEEL
esprovision-0.1.dist-info/entry_points.txt
esprovision-0.1.dist-info/top_level.txt
esprovision-0.1.dist-info/RECORD
